[
    {
        "key": "cmd+up",
        "command": "editor.action.moveLinesUpAction",
        "when": "editorTextFocus && !editorReadonly"
    },
    {
        "key": "alt+up",
        "command": "-editor.action.moveLinesUpAction",
        "when": "editorTextFocus && !editorReadonly"
    },
    {
        "key": "cmd+down",
        "command": "editor.action.moveLinesDownAction",
        "when": "editorTextFocus && !editorReadonly"
    },
    {
        "key": "alt+down",
        "command": "-editor.action.moveLinesDownAction",
        "when": "editorTextFocus && !editorReadonly"
    },
    {
        "key": "cmd+d",
        "command": "editor.action.copyLinesDownAction",
        "when": "editorTextFocus && !editorReadonly"
    },
    {
        "key": "cmd+shift+alt+down",
        "command": "-editor.action.copyLinesDownAction",
        "when": "editorTextFocus && !editorReadonly"
    },
    {
        "key": "cmd+`",
        "command": "outdent",
        "when": "editorTextFocus && !editorReadonly && !editorTabMovesFocus"
    },
    {
        "key": "shift+tab",
        "command": "-outdent",
        "when": "editorTextFocus && !editorReadonly && !editorTabMovesFocus"
    },
    {
        "key": "cmd+shift+f",
        "command": "editor.action.format"
    },
    {
        "key": "cmd+alt+l",
        "command": "liquid.formatDocument",
        "when": "editorTextFocus"
    },
    {
        "key": "cmd+shift+l",
        "command": "-liquid.formatDocument",
        "when": "editorTextFocus"
    }
]